valvetraces/__init__.py
valvetraces-0.0.5.dist-info/LICENSE
valvetraces-0.0.5.dist-info/METADATA
valvetraces-0.0.5.dist-info/WHEEL
valvetraces-0.0.5.dist-info/entry_points.txt
valvetraces-0.0.5.dist-info/top_level.txt
valvetraces-0.0.5.dist-info/RECORD
