Metadata-Version: 2.1
Name: valvetraces
Version: 0.0.5
Summary: Interact with Valve's GFX trace system
Home-page: https://gitlab.freedesktop.org/mupuf/valve-infra/-/tree/master/valvetraces
Author: Martin Peres
Author-email: martin.peres@mupuf.org
License: UNKNOWN
Project-URL: Bug Tracker, https://gitlab.freedesktop.org/mupuf/valve-infra/issues
Platform: UNKNOWN
Classifier: Programming Language :: Python :: 3
Classifier: License :: OSI Approved :: MIT License
Classifier: Operating System :: OS Independent
Classifier: Development Status :: 7 - Inactive
Requires-Python: >=3.6
License-File: LICENSE
Requires-Dist: requests (<3,>=2)
Requires-Dist: gfxinfo-mupuf (>=0.0.5)
Requires-Dist: humanize (>=3.3.0)
Requires-Dist: Pillow (>=5.4.0)
Requires-Dist: click (>=7.1.2)
Requires-Dist: valve-gfx-ci.valvetraces (>=0.0.6)
Requires-Dist: backports.cached-property ; python_version < "3.8"
